odoo/addons/hr_timesheet_task_required/README.rst
odoo/addons/hr_timesheet_task_required/__init__.py
odoo/addons/hr_timesheet_task_required/__manifest__.py
odoo/addons/hr_timesheet_task_required/i18n/de.po
odoo/addons/hr_timesheet_task_required/i18n/es.po
odoo/addons/hr_timesheet_task_required/i18n/fr.po
odoo/addons/hr_timesheet_task_required/i18n/hr_timesheet_task_required.pot
odoo/addons/hr_timesheet_task_required/models/__init__.py
odoo/addons/hr_timesheet_task_required/models/account_analytic_line.py
odoo/addons/hr_timesheet_task_required/static/description/icon.png
odoo/addons/hr_timesheet_task_required/tests/__init__.py
odoo/addons/hr_timesheet_task_required/tests/test_hr_timesheet_task_required.py
odoo/addons/hr_timesheet_task_required/views/account_analytic_line.xml
odoo11_addon_hr_timesheet_task_required-11.0.1.0.2.dist-info/METADATA
odoo11_addon_hr_timesheet_task_required-11.0.1.0.2.dist-info/WHEEL
odoo11_addon_hr_timesheet_task_required-11.0.1.0.2.dist-info/top_level.txt
odoo11_addon_hr_timesheet_task_required-11.0.1.0.2.dist-info/RECORD
